{
  "problem_id": "05_qaoa_maxcut",
  "instance_id": "medium",
  "depth": 2,
  "coarse_shots": 24,
  "refined_shots": 96,
  "trials": 6,
  "classical_optimum": {
    "value": 4,
    "assignment": [
      1,
      0,
      1,
      0
    ]
  },
  "aggregate": {
    "coarse_expectation": {
      "mean": 3.295138888888889,
      "std": 0.201735812296585,
      "ci95": 0.16142226897102238
    },
    "refined_expectation": {
      "mean": 2.831597222222222,
      "std": 0.25053472905560004,
      "ci95": 0.20046953468400064
    },
    "refined_best_sample": {
      "mean": 4,
      "std": 0,
      "ci95": 0
    },
    "mean_optimality_gap": 1.1684027777777781
  },
  "best_trial": {
    "Trial": 4,
    "BestBetas": [
      0.1,
      0.5
    ],
    "BestGammas": [
      0.9,
      0.3
    ],
    "BestBeta": 0.1,
    "BestGamma": 0.9,
    "CoarseExpectation": 3.3541666666666665,
    "RefinedExpectation": 3.109375,
    "RefinedBestSample": 4,
    "RefinedAssignment": [
      0,
      1,
      0,
      1
    ]
  },
  "trial_results": [
    {
      "Trial": 1,
      "BestBetas": [
        0.1,
        0.9
      ],
      "BestGammas": [
        0.3,
        0.1
      ],
      "BestBeta": 0.1,
      "BestGamma": 0.3,
      "CoarseExpectation": 3.0833333333333335,
      "RefinedExpectation": 2.4583333333333335,
      "RefinedBestSample": 4,
      "RefinedAssignment": [
        1,
        0,
        1,
        0
      ]
    },
    {
      "Trial": 2,
      "BestBetas": [
        0.1,
        0.5
      ],
      "BestGammas": [
        0.9,
        0.3
      ],
      "BestBeta": 0.1,
      "BestGamma": 0.9,
      "CoarseExpectation": 3.3333333333333335,
      "RefinedExpectation": 3.0416666666666665,
      "RefinedBestSample": 4,
      "RefinedAssignment": [
        1,
        0,
        1,
        0
      ]
    },
    {
      "Trial": 3,
      "BestBetas": [
        0.1,
        0.3
      ],
      "BestGammas": [
        0.9,
        0.3
      ],
      "BestBeta": 0.1,
      "BestGamma": 0.9,
      "CoarseExpectation": 3.5833333333333335,
      "RefinedExpectation": 2.9479166666666665,
      "RefinedBestSample": 4,
      "RefinedAssignment": [
        1,
        0,
        1,
        0
      ]
    },
    {
      "Trial": 4,
      "BestBetas": [
        0.1,
        0.5
      ],
      "BestGammas": [
        0.9,
        0.3
      ],
      "BestBeta": 0.1,
      "BestGamma": 0.9,
      "CoarseExpectation": 3.3541666666666665,
      "RefinedExpectation": 3.109375,
      "RefinedBestSample": 4,
      "RefinedAssignment": [
        0,
        1,
        0,
        1
      ]
    },
    {
      "Trial": 5,
      "BestBetas": [
        0.7,
        0.1
      ],
      "BestGammas": [
        0.9,
        0.9
      ],
      "BestBeta": 0.7,
      "BestGamma": 0.9,
      "CoarseExpectation": 3.375,
      "RefinedExpectation": 2.6354166666666665,
      "RefinedBestSample": 4,
      "RefinedAssignment": [
        0,
        1,
        0,
        1
      ]
    },
    {
      "Trial": 6,
      "BestBetas": [
        0.1,
        0.5
      ],
      "BestGammas": [
        0.9,
        0.5
      ],
      "BestBeta": 0.1,
      "BestGamma": 0.9,
      "CoarseExpectation": 3.0416666666666665,
      "RefinedExpectation": 2.796875,
      "RefinedBestSample": 4,
      "RefinedAssignment": [
        0,
        1,
        0,
        1
      ]
    }
  ]
}
